arganic/__init__.py
arganic/arguments.py
arganic/validators.py
Arganic-0.1.0.dist-info/LICENSE
Arganic-0.1.0.dist-info/METADATA
Arganic-0.1.0.dist-info/WHEEL
Arganic-0.1.0.dist-info/top_level.txt
Arganic-0.1.0.dist-info/RECORD
