Metadata-Version: 2.1
Name: Arganic
Version: 0.1.0
Summary: Arganic is a simple and lightweight Python library making it easy to manage Arguments for Classes, Methods or Functions.
Author: Kiwea
License: GNU General Public License v3 (GPLv3)
Project-URL: Homepage, https://github.com/kiwea/arganic
Project-URL: Changelog, https://github.com/kiwea/arganic/releases
Project-URL: Issues, https://github.com/kiwea/arganic/issues
Project-URL: CI, https://github.com/kiwea/arganic/actions
Classifier: License :: OSI Approved :: GNU General Public License v3 (GPLv3)
Requires-Python: >=3.12
License-File: LICENSE
Provides-Extra: test
Requires-Dist: pytest ; extra == 'test'
Requires-Dist: pytest-cov ; extra == 'test'
Requires-Dist: mkdocs ; extra == 'test'
Requires-Dist: mkdocs-material ; extra == 'test'
Requires-Dist: mkdocstrings[python] ; extra == 'test'
Requires-Dist: mkdocs-section-index ; extra == 'test'
